[
  {
    "type": "ltminigames:set_difficulty",
    "difficulty": "normal"
  },
  {
    "type": "lt:common/playing",
    "game_type": "adventure",
    "join_late_with_role": "participant"
  },
  "ltminigames:spectator_chase",
  {
    "type": "ltminigames:microgames",
    "games": [
      "lt:block_party",
      "lt:block_party"
    ],
    "games_per_round": 2
  },
  {
    "type": "ltminigames:victory_points",
    "points_per_question": 1,
    "points_per_block_collected": 1,
    "points_per_game_won": 1
  },
  "lt:teams/red_blue",
  "ltminigames:teams",
  {
    "type": "ltminigames:team_chat",
    "chat_type": "lt:team_chat"
  },
  "ltminigames:river_race_overlord",
  {
    "type": "ltminigames:trivia",
    "zones": [
      {
        "zone_id": 1,
        "questions": [
          {
            "difficulty": "easy",
            "question": "Can you dye sheep?",
            "answers": [
              {
                "text": "Yes",
                "correct": true
              },
              {
                "text": "Maybe?",
                "correct": false
              },
              {
                "text": "Absolutely Not.",
                "correct": false
              },
              {
                "text": "Once in a blue moon?",
                "correct": false
              }
            ]
          },
          {
            "difficulty": "hard",
            "question": "Moon is red?",
            "answers": [
              {
                "text": "No",
                "correct": true
              },
              {
                "text": "Perhaps?",
                "correct": false
              },
              {
                "text": "If it's a blood moon.",
                "correct": false
              },
              {
                "text": "I don't know!",
                "correct": false
              }
            ]
          }
        ]
      }
    ]
  }
]