{
  "type": "ltminigames:donation_package",
  "id": "leaky_pockets",
  "package_type": "sabotage_package",
  "category": "small",
  "player_select": "specific",
  "name": {"translate": "ltminigames.minigame.donation.leaky_pockets"},
  "description": {"translate": "ltminigames.minigame.donation.leaky_pockets.description"},
  "donation_amount": 10.0,
  "notification": {
    "message": {
      "translate": "ltminigames.minigame.donation.leaky_pockets.toast",
      "color": "light_purple"
    },
    "icon": {"item": "ltextras:tropicoin"},
    "sentiment": "neutral",
    "sound": "ltminigames:sabotage_receive"
  },
  "receive_actions": {
    "type": "ltminigames:give_effect",
    "effects": [
      {
        "type": "ltminigames:leaky_pockets",
        "seconds": 15,
        "amplifier": 3,
        "particles": false,
        "show_icon": false
      }
    ]
  }
}